adafruit_json_stream.py
adafruit_circuitpython_json_stream-0.9.3.dist-info/licenses/LICENSE
adafruit_circuitpython_json_stream-0.9.3.dist-info/METADATA
adafruit_circuitpython_json_stream-0.9.3.dist-info/WHEEL
adafruit_circuitpython_json_stream-0.9.3.dist-info/top_level.txt
adafruit_circuitpython_json_stream-0.9.3.dist-info/RECORD
